tagged_dataclasses/__init__.py
tagged_dataclasses/tagged_dataclasses.py
tagged_dataclasses-0.0.2.dist-info/WHEEL
tagged_dataclasses-0.0.2.dist-info/METADATA
tagged_dataclasses-0.0.2.dist-info/RECORD
